<?xml version="1.0"?>
<UserPolicy xmlns:xsi="http://www.w3.org/2001/XMLSchema-instance" xmlns:xsd="http://www.w3.org/2001/XMLSchema">
  <IsAdministrator>false</IsAdministrator>
  <IsHidden>false</IsHidden>
  <IsHiddenRemotely>false</IsHiddenRemotely>
  <IsHiddenFromUnusedDevices>false</IsHiddenFromUnusedDevices>
  <IsDisabled>false</IsDisabled>
  <MaxParentalRating xsi:nil="true" />
  <BlockedTags />
  <IsTagBlockingModeInclusive>false</IsTagBlockingModeInclusive>
  <EnableUserPreferenceAccess>true</EnableUserPreferenceAccess>
  <AccessSchedules />
  <BlockUnratedItems />
  <EnableRemoteControlOfOtherUsers>false</EnableRemoteControlOfOtherUsers>
  <EnableSharedDeviceControl>true</EnableSharedDeviceControl>
  <EnableRemoteAccess>true</EnableRemoteAccess>
  <EnableLiveTvManagement>true</EnableLiveTvManagement>
  <EnableLiveTvAccess>true</EnableLiveTvAccess>
  <EnableMediaPlayback>true</EnableMediaPlayback>
  <EnableAudioPlaybackTranscoding>true</EnableAudioPlaybackTranscoding>
  <EnableVideoPlaybackTranscoding>true</EnableVideoPlaybackTranscoding>
  <EnablePlaybackRemuxing>true</EnablePlaybackRemuxing>
  <EnableContentDeletion>false</EnableContentDeletion>
  <EnableContentDeletionFromFolders />
  <EnableContentDownloading>true</EnableContentDownloading>
  <EnableSubtitleDownloading>false</EnableSubtitleDownloading>
  <EnableSubtitleManagement>false</EnableSubtitleManagement>
  <EnableSyncTranscoding>true</EnableSyncTranscoding>
  <EnableMediaConversion>true</EnableMediaConversion>
  <EnabledChannels />
  <EnableAllChannels>true</EnableAllChannels>
  <EnabledFolders />
  <EnableAllFolders>true</EnableAllFolders>
  <InvalidLoginAttemptCount>0</InvalidLoginAttemptCount>
  <EnablePublicSharing>true</EnablePublicSharing>
  <RemoteClientBitrateLimit>0</RemoteClientBitrateLimit>
  <AuthenticationProviderId>Emby.Server.Implementations.Library.DefaultAuthenticationProvider</AuthenticationProviderId>
  <ExcludedSubFolders />
  <SimultaneousStreamLimit>0</SimultaneousStreamLimit>
  <EnabledDevices />
  <EnableAllDevices>true</EnableAllDevices>
</UserPolicy>